libname/__init__.py
libname/client.py
libname/server.py
queueconfirmer/__init__.py
queueconfirmer/client.py
queueconfirmer/server.py
venv/__init__.py
venv/lib/__init__.py
queue_confirmer-0.0.6.dist-info/METADATA
queue_confirmer-0.0.6.dist-info/WHEEL
queue_confirmer-0.0.6.dist-info/top_level.txt
queue_confirmer-0.0.6.dist-info/RECORD
