Metadata-Version: 2.1
Name: queue_confirmer
Version: 0.0.6
Summary: Handling server and client information
Author: MichaeCarlsonDev (Michael Carlson)
Author-email: <soprano19522@gmail.com>
Keywords: python,sockets,solar car,threading
Classifier: Development Status :: 1 - Planning
Classifier: Intended Audience :: Developers
Classifier: Programming Language :: Python :: 3
Classifier: Operating System :: Unix
Classifier: Operating System :: MacOS :: MacOS X
Classifier: Operating System :: Microsoft :: Windows
